skvideo/__init__.py
skvideo/setup.py
skvideo/datasets/__init__.py
skvideo/datasets/setup.py
skvideo/datasets/data/bigbuckbunny.mp4
skvideo/datasets/data/bikes.mp4
skvideo/datasets/data/carphone_distorted.mp4
skvideo/datasets/data/carphone_pristine.mp4
skvideo/io/__init__.py
skvideo/io/abstract.py
skvideo/io/avconv.py
skvideo/io/avprobe.py
skvideo/io/ffmpeg.py
skvideo/io/ffprobe.py
skvideo/io/io.py
skvideo/io/mprobe.py
skvideo/measure/Li3DDCT.py
skvideo/measure/__init__.py
skvideo/measure/brisque.py
skvideo/measure/mae.py
skvideo/measure/mse.py
skvideo/measure/msssim.py
skvideo/measure/niqe.py
skvideo/measure/psnr.py
skvideo/measure/scene.py
skvideo/measure/setup.py
skvideo/measure/ssim.py
skvideo/measure/strred.py
skvideo/measure/videobliinds.py
skvideo/measure/viideo.py
skvideo/measure/data/frames_modelparameters.mat
skvideo/measure/data/niqe_image_params.mat
skvideo/motion/__init__.py
skvideo/motion/block.py
skvideo/motion/gme.py
skvideo/tests/__init__.py
skvideo/tests/test_IOfail.py
skvideo/tests/test_ffmpeg.py
skvideo/tests/test_libav.py
skvideo/tests/test_measure.py
skvideo/tests/test_motion.py
skvideo/tests/test_path.py
skvideo/tests/test_pattern.py
skvideo/tests/test_scenedet.py
skvideo/tests/test_vread.py
skvideo/tests/test_vreader.py
skvideo/tests/test_vwrite.py
skvideo/utils/__init__.py
skvideo/utils/edge.py
skvideo/utils/image.py
skvideo/utils/mscn.py
skvideo/utils/stats.py
skvideo/utils/stpyr.py
skvideo/utils/xmltodict.py
absolutely_not_scikit_video-1.1.12.dist-info/COPYING
absolutely_not_scikit_video-1.1.12.dist-info/LICENSE.txt
absolutely_not_scikit_video-1.1.12.dist-info/METADATA
absolutely_not_scikit_video-1.1.12.dist-info/WHEEL
absolutely_not_scikit_video-1.1.12.dist-info/top_level.txt
absolutely_not_scikit_video-1.1.12.dist-info/RECORD
